cdk_k3s_cluster/__init__.py
cdk_k3s_cluster/py.typed
cdk_k3s_cluster/_jsii/__init__.py
cdk_k3s_cluster/_jsii/cdk-k3s-cluster@0.0.59.jsii.tgz
cdk_k3s_cluster-0.0.59.dist-info/LICENSE
cdk_k3s_cluster-0.0.59.dist-info/METADATA
cdk_k3s_cluster-0.0.59.dist-info/WHEEL
cdk_k3s_cluster-0.0.59.dist-info/top_level.txt
cdk_k3s_cluster-0.0.59.dist-info/RECORD
