Metadata-Version: 2.1
Name: cdk-k3s-cluster
Version: 0.0.59
Summary: A JSII construct lib to deploy a K3s cluster on AWS with CDK
Home-page: https://github.com/aws-samples/aws-cdk-for-k3scluster
Author: Massimo Re Ferre<mreferre@amazon.com>
License: MIT
Project-URL: Source, https://github.com/aws-samples/aws-cdk-for-k3scluster
Platform: UNKNOWN
Classifier: Intended Audience :: Developers
Classifier: Operating System :: OS Independent
Classifier: Programming Language :: JavaScript
Classifier: Programming Language :: Python :: 3 :: Only
Classifier: Programming Language :: Python :: 3.6
Classifier: Programming Language :: Python :: 3.7
Classifier: Programming Language :: Python :: 3.8
Classifier: Programming Language :: Python :: 3.9
Classifier: Typing :: Typed
Classifier: Development Status :: 5 - Production/Stable
Classifier: License :: OSI Approved
Requires-Python: >=3.6
License-File: LICENSE
Requires-Dist: aws-cdk.aws-autoscaling (<2.0.0,>=1.62.0)
Requires-Dist: aws-cdk.aws-ec2 (<2.0.0,>=1.62.0)
Requires-Dist: aws-cdk.aws-iam (<2.0.0,>=1.62.0)
Requires-Dist: aws-cdk.aws-lambda (<2.0.0,>=1.62.0)
Requires-Dist: aws-cdk.aws-logs (<2.0.0,>=1.62.0)
Requires-Dist: aws-cdk.aws-s3 (<2.0.0,>=1.62.0)
Requires-Dist: aws-cdk.core (<2.0.0,>=1.62.0)
Requires-Dist: aws-cdk.custom-resources (<2.0.0,>=1.62.0)
Requires-Dist: constructs (<4.0.0,>=3.2.27)
Requires-Dist: jsii (<2.0.0,>=1.55.1)
Requires-Dist: publication (>=0.0.3)
